{"logs": {"1": {"action": "connect", "status": "error", "details": "Failed to connect to Dobot: \"port\" must be None or a string, not <class 'list'>"}, "8": {"action": "connect", "status": "error", "details": "Failed to connect to Dobot: could not open port 'COM5': OSError(22, 'O tempo limite do sem\u00e1foro expirou.', None, 121)"}, "9": {"action": "connect", "status": "error", "details": "Failed to connect to Dobot: could not open port 'COM7': PermissionError(13, 'Acesso negado.', None, 5)"}, "10": {"action": "connect", "status": "error", "details": "Failed to connect to Dobot: could not open port 'COM7': PermissionError(13, 'Acesso negado.', None, 5)"}, "11": {"action": "update_pose", "status": "success", "details": "Updated pose to x=279.54803466796875, y=-17.41131591796875, z=142.82310485839844, r=-3.563995361328125"}, "12": {"action": "init", "status": "success", "details": "Connected to Dobot on port COM7"}, "13": {"action": "update_pose", "status": "success", "details": "Updated pose to x=220.67747497558594, y=-3.3020944595336914, z=117.55362701416016, r=-2.70611572265625"}, "14": {"action": "move", "status": "success", "details": "Moved to x=40.0, y=40.0, z=40.0, r=0.0"}}}